CHANGES.txt
COPYRIGHT.txt
LICENSE.txt
README.txt
buildout.cfg
setup.cfg
setup.py
bootstrap/bootstrap.py
docs/Makefile
docs/README.rst
docs/README.txt
docs/api.rst
docs/api_base.rst
docs/api_sqlite.rst
docs/api_ui.rst
docs/bugs.rst
docs/changes.rst
docs/conf.py
docs/contents.rst
docs/copyright.rst
docs/index.rst
docs/intro.rst
docs/license.rst
docs/make.bat
docs/todo.rst
docs/_templates/docindex.template
src/ulif/__init__.py
src/ulif.pynotify.egg-info/PKG-INFO
src/ulif.pynotify.egg-info/SOURCES.txt
src/ulif.pynotify.egg-info/dependency_links.txt
src/ulif.pynotify.egg-info/entry_points.txt
src/ulif.pynotify.egg-info/namespace_packages.txt
src/ulif.pynotify.egg-info/not-zip-safe
src/ulif.pynotify.egg-info/requires.txt
src/ulif.pynotify.egg-info/top_level.txt
src/ulif/pynotify/README.txt
src/ulif/pynotify/__init__.py
src/ulif/pynotify/base.py
src/ulif/pynotify/sqlite.py
src/ulif/pynotify/tests/__init__.py
src/ulif/pynotify/tests/test_base.py
src/ulif/pynotify/tests/test_config.py
src/ulif/pynotify/tests/test_scripts.py
src/ulif/pynotify/tests/test_sqlite.py
src/ulif/pynotify/ui/__init__.py
src/ulif/pynotify/ui/config.py
src/ulif/pynotify/ui/pynotify.py
src/ulif/pynotify/ui/pynotifyctl.py