Metadata-Version: 1.0
Name: ulif.pynotify
Version: 0.2
Summary: Helpers to bridge different Python envs and OpenOffice.org.
Home-page: http://pypi.python.org/pypi/ulif.pynotify
Author: Uli Fouquet
Author-email: uli at gnufix.de
License: GPL
Keywords: filesystem changes monitor watchdog inotify
Platform: UNKNOWN
Classifier: Development Status :: 3 - Alpha
Classifier: Framework :: Buildout
Classifier: Programming Language :: Python
Classifier: Topic :: Software Development :: Libraries :: Python Modules
Classifier: License :: OSI Approved :: GNU General Public License (GPL)
